Workbook

Sheet Version
A1: BANCO DE PREGUNTAS · SOLARIS MERIT NEIVA
A2: Versión del banco | B2: 2026.09.26-n
A3: Fecha de generación | B3: 2026-09-26
A4: Huella de contenido | B4: 95953e8a9d
A6: Preguntas del banco principal | B6: 626
A7: Casos del banco principal | B7: 214
A8: Preguntas del banco de repaso | B8: 291
A9: Situaciones comportamentales activas | B9: 138
A11: Ventaja de longitud de la correcta · principal | B11: -3 caracteres
A12: Ventaja de longitud de la correcta · repaso | B12: +35 caracteres
A14: Cómo verificar que tiene la última versión
A15: 1. Compare la huella de contenido con la que reporta la app en la tarjeta del banco.
A16: 2. Si coinciden, está usando el mismo archivo. Si no, actualice el Excel del repositorio.
A17: 3. La versión de sw.js es otra cosa: controla la caché del celular, no el contenido del banco.
A18: Preguntas de aptitudes para práctica (hoja Basicas) | B18: 114
A19: La hoja Basicas trae solo aptitudes (lectura, cálculo, análisis, ofimática): son práctica y no entran en el ponderado.
A20: Filas inactivas que se conservan en el archivo (comportamentales): 30
A21: Las filas con activa = NO no se usan en los simulacros; se conservan por historia y se pueden reactivar.

Sheet Funcionales
A1: id | B1: concurso | C1: eje | D1: nivel | E1: caso_id | F1: caso | G1: texto_caso | H1: enunciado | I1: a | J1: b | K1: c | L1: respuesta | M1: explicacion | N1: porque_no | O1: fuente | P1: activa | Q1: dificultad | R1: tipo_v2
A2: F0001 | B2: PS 2782 de 2026 - ESE 2 - HUHMP Neiva | C2: Sistema de salud y Ley 100 de 1993 | D2: Profesional | E2: C001 | F2: Caso 001 | G2: La E.S.E. recibe un derecho de petición de un ciudadano que afirma que, por ser el hospital una entidad pública, toda su contratación debe adelantarse por licitación pública de la Ley 80 de 1993. El jefe de la oficina jurídica pide concepto. | H2: ¿Cuál es el régimen contractual aplicable a la E.S.E.? | I2: El derecho privado, pudiendo incluir discrecionalmente las cláusulas excepcionales | J2: El Estatuto General de Contratación de la Administración Pública, sin excepciones | K2: El régimen de las empresas industriales y comerciales del Estado del orden nacional | L2: a | M2: El numeral 6 del artículo 195 de la Ley 100 de 1993 dispone que en materia contractual las E.S.E. se rigen por el derecho privado, con la posibilidad de pactar discrecionalmente las cláusulas excepcionales. | N2: «El Estatuto General de Contratación de…» desconoce el régimen exceptuado del artículo 195.6; «El régimen de las empresas industriales…» traslada un régimen que la ley no previó para las E.S.E., que son una categoría especial de entidad pública descentralizada. | O2: Ley 100 de 1993, art. 195 num. 6 | P2: SI | Q2: Basica | R2: repaso
A3: F0002 | B3: PS 2782 de 2026 - ESE 2 - HUHMP Neiva | C3: Sistema de salud y Ley 100 de 1993 | D3: Profesional | E3: C001 | F3: Caso 001 | G3: La E.S.E. recibe un derecho de petición de un ciudadano que afirma que, por ser el hospital una entidad pública, toda su contratación debe adelantarse por licitación pública de la Ley 80 de 1993. El jefe de la oficina jurídica pide concepto. | H3: El ciudadano insiste en que, al aplicar derecho privado, la E.S.E. queda libre de los principios de la función administrativa. La respuesta correcta es: | I3: Es cierto: el régimen privado excluye los principios del artículo 209 de la Constitución | J3: Los principios de la función administrativa y de la gestión fiscal siguen aplicando a la actividad contractual | K3: Solo aplican los principios cuando el contrato supere la menor cuantía | L3: b | M3: El artículo 13 de la Ley 1150 de 2007 obliga a las entidades con régimen contractual excepcional a aplicar los principios de la función administrativa y de la gestión fiscal de los artículos 209 y 267 de la Constitución. | N3: «Es cierto: el régimen privado excluye…» y «Solo aplican los principios cuando el…» confunden el régimen sustantivo aplicable con la naturaleza pública de los recursos y de la función, que no admite excepción por cuantía. | O3: Ley 1150 de 2007, art. 13; C.P. arts. 209 y 267 | P3: SI | Q3: Basica | R3: repaso
A4: F0003 | B4: PS 2782 de 2026 - ESE 2 - HUHMP Neiva | C4: Sistema de salud y Ley 100 de 1993 | D4: Profesional | E4: C001 | F4: Caso 001 | G4: La E.S.E. recibe un derecho de petición de un ciudadano que afirma que, por ser el hospital una entidad pública, toda su contratación debe adelantarse por licitación pública de la Ley 80 de 1993. El jefe de la oficina jurídica pide concepto. | H4: Sobre la naturaleza jurídica de la E.S.E., lo correcto es afirmar que: | I4: Es una sociedad de economía mixta sujeta al control de la Superintendencia de Sociedades | J4: Es un establecimiento público del orden nacional adscrito al Ministerio de Salud | K4: Es una categoría especial de entidad pública descentralizada, con personería jurídica, patrimonio propio y autonomía administrativa | L4: c | M4: El artículo 194 de la Ley 100 de 1993 define a las E.S.E. como categoría especial de entidad pública descentralizada, con personería jurídica, patrimonio propio y autonomía administrativa. | N4: «Es un establecimiento público del orden…» y «Es una sociedad de economía mixta…» asignan naturalezas y controles que no corresponden: la E.S.E. departamental se crea por ordenanza y es vigilada por la Superintendencia Nacional de Salud. | O4: Ley 100 de 1993, art. 194; Decreto 1876 de 1994 | P4: SI | Q4: Basica | R4: repaso
A5: F0004 | B5: PS 2782 de 2026 - ESE 2 - HUHMP Neiva | C5: Sistema de salud y Ley 100 de 1993 | D5: Profesional | E5: C002 | F5: Caso 002 | G5: En una mesa de trabajo sobre facturación, un contratista sostiene que el hospital puede cobrar copagos a un usuario del régimen subsidiado clasificado en el nivel I del Sisbén por una hospitalización. | H5: Frente a los pagos moderadores, lo correcto es: | I5: Toda la población afiliada paga cuotas moderadoras y copagos en igual proporción | J5: Los copagos son de libre fijación por cada prestador | K5: Los pagos moderadores se aplican según la capacidad socioeconómica del afiliado y existen servicios exceptuados | L5: c | M5: El artículo 187 de la Ley 100 de 1993 y sus normas reglamentarias establecen que los pagos moderadores se fijan según el ingreso o clasificación socioeconómica del afiliado, con servicios exceptuados de cobro. | N5: «Toda la población afiliada paga cuotas…» desconoce la progresividad legal; «Los copagos son de libre fijación…» confunde el cobro al usuario con la negociación tarifaria entre prestador y pagador. | O5: Ley 100 de 1993, art. 187 | P5: SI | Q5: Basica | R5: repaso
A6: F0005 | B6: PS 2782 de 2026 - ESE 2 - HUHMP Neiva | C6: Sistema de salud y Ley 100 de 1993 | D6: Profesional | E6: C002 | F6: Caso 002 | G6: En una mesa de trabajo sobre facturación, un contratista sostiene que el hospital puede cobrar copagos a un usuario del régimen subsidiado clasificado en el nivel I del Sisbén por una hospitalización. | H6: El usuario llega remitido y sin autorización de la EPS a urgencias. El hospital debe: | I6: Exigir la autorización antes de valorar al paciente | J6: Aplazar la atención hasta verificar la afiliación en el ADRES | K6: Prestar la atención inicial de urgencias sin exigir autorización previa ni pago | L6: c | M6: La atención inicial de urgencias es obligatoria y no puede condicionarse a autorización previa ni a pago, conforme a la Ley 100 y al artículo 14 de la Ley 1751 de 2015. | N6: «Exigir la autorización antes de valorar…» y «Aplazar la atención hasta verificar la…» condicionan una atención que la ley define como incondicionada; la verificación de derechos es un trámite posterior y administrativo. | O6: Ley 1751 de 2015, art. 14; Ley 100 de 1993, art. 168 | P6: SI | Q6: Basica | R6: repaso
A7: F0006 | B7: PS 2782 de 2026 - ESE 2 - HUHMP Neiva | C7: Sistema de salud y Ley 100 de 1993 | D7: Profesional | E7: C002 | F7: Caso 002 | G7: En una mesa de trabajo sobre facturación, un contratista sostiene que el hospital puede cobrar copagos a un usuario del régimen subsidiado clasificado en el nivel I del Sisbén por una hospitalización. | H7: Los recursos de la seguridad social en salud: | I7: Tienen destinación específica y no pueden destinarse ni utilizarse para fines distintos | J7: Pueden destinarse a gastos generales del departamento si hay superávit | K7: Pierden su destinación al ingresar al presupuesto de la E.S.E | L7: a | M7: El artículo 48 de la Constitución prohíbe destinar o utilizar los recursos de las instituciones de la seguridad social para fines diferentes a ella. | N7: «Pueden destinarse a gastos generales del…» y «Pierden su destinación al ingresar al…» suponen una pérdida de destinación que la Constitución no permite, cualquiera sea el momento presupuestal. | O7: C.P. art. 48; Ley 100 de 1993 | P7: SI | Q7: Basica | R7: repaso
A8: F0007 | B8: PS 2782 de 2026 - ESE 2 - HUHMP Neiva | C8: Sistema de salud y Ley 100 de 1993 | D8: Técnico | E8: C003 | F8: Caso 003 | G8: Un técnico de facturación debe explicar a un usuario nuevo la diferencia entre los regímenes del SGSSS y las rutas de afiliación. | H8: La afiliación al régimen subsidiado corresponde a: | I8: Población sin capacidad de pago identificada mediante la encuesta del Sisbén o listados censales | J8: Trabajadores dependientes con contrato laboral vigente | K8: Pensionados con mesada superior a dos salarios mínimos | L8: a | M8: El régimen subsidiado cubre a la población sin capacidad de pago, identificada mediante los instrumentos de focalización vigentes. | N8: «Trabajadores dependientes con contrato laboral vigente» y «Pensionados con mesada superior a dos…» describen afiliados cotizantes del régimen contributivo. | O8: Ley 100 de 1993, arts. 157 y 211 | P8: SI | Q8: Basica | R8: repaso
A9: F0008 | B9: PS 2782 de 2026 - ESE 2 - HUHMP Neiva | C9: Sistema de salud y Ley 100 de 1993 | D9: Técnico | E9: C003 | F9: Caso 003 | G9: Un técnico de facturación debe explicar a un usuario nuevo la diferencia entre los regímenes del SGSSS y las rutas de afiliación. | H9: El Sistema de Afiliación Transaccional (SAT) sirve para: | I9: Autorizar los medicamentos no financiados con la UPC | J9: Liquidar la nómina del personal asistencial | K9: Registrar y consultar en línea la afiliación y sus novedades | L9: c | M9: El SAT es el sistema dispuesto para el registro de la afiliación y el reporte de novedades de los afiliados al SGSSS. | N9: «Liquidar la nómina del personal asistencial» y «Autorizar los medicamentos no financiados con…» corresponden a procesos de talento humano y a trámites de prestaciones, ajenos al SAT. | O9: Decreto 780 de 2016, (Decreto Único Reglamentario del Sector Salud), Libro 2, Parte 1 | P9: SI | Q9: Basica | R9: repaso
A10: F0009 | B10: PS 2782 de 2026 - ESE 2 - HUHMP Neiva | C10: Sistema de salud y Ley 100 de 1993 | D10: Técnico | E10: C003 | F10: Caso 003 | G10: Un técnico de facturación debe explicar a un usuario nuevo la diferencia entre los regímenes del SGSSS y las rutas de afiliación. | H10: Si el usuario aparece como no afiliado y requiere atención no urgente, el trámite correcto es: | I10: Negar la atención y retirar al usuario | J10: Afiliarlo directamente el hospital a la EPS que elija el funcionario | K10: Orientarlo sobre la afiliación de oficio y la ruta con la entidad territorial, sin perjuicio de la atención que la ley ordena | L10: c | M10: El prestador orienta al usuario sobre la afiliación de oficio y la competencia de la entidad territorial, sin que ello afecte las atenciones obligatorias por ley. | N10: «Negar la atención y retirar al…» vulnera el deber de información y atención; «Afiliarlo directamente el hospital a la…» atribuye al prestador una facultad de afiliación que no tiene y desconoce la libre elección. | O10: Decreto 780 de 2016; Ley 1751 de 2015, art. 8 | P10: SI | Q10: Basica | R10: repaso
A11: F0010 | B11: PS 2782 de 2026 - ESE 2 - HUHMP Neiva | C11: Sistema de salud y Ley 100 de 1993 | D11: Profesional | E11: C004 | F11: Caso 004 | G11: La gerencia solicita un informe sobre el flujo de recursos y la contratación con las EPS para la vigencia. | H11: El giro directo a las IPS tiene como finalidad: | I11: Reemplazar la facturación del prestador | J11: Eliminar la auditoría de cuentas médicas | K11: Asegurar el flujo oportuno de recursos desde el pagador hacia el prestador | L11: c | M11: El giro directo busca garantizar el flujo y protección de los recursos hacia los prestadores, sin sustituir los procesos de facturación ni de auditoría. | N11: «Reemplazar la facturación del prestador» y «Eliminar la auditoría de cuentas médicas» suprimen procesos que se mantienen: facturar y auditar siguen siendo obligaciones de las partes. | O11: Ley 1438 de 2011; Decreto 780 de 2016, (Decreto Único Reglamentario del Sector Salud) | P11: SI | Q11: Basica | R11: repaso
A12: F0011 | B12: PS 2782 de 2026 - ESE 2 - HUHMP Neiva | C12: Sistema de salud y Ley 100 de 1993 | D12: Profesional | E12: C004 | F12: Caso 004 | G12: La gerencia solicita un informe sobre el flujo de recursos y la contratación con las EPS para la vigencia. | H12: Ante glosas de la EPS, el término y el trámite correctos son: | I12: El prestador debe aceptarlas todas para no afectar el flujo de caja | J12: Existe un procedimiento reglado de respuesta a glosas con términos definidos y conciliación posterior | K12: Las glosas solo se discuten ante el juez administrativo | L12: b | M12: El manual único de glosas fija el trámite y los términos para formularlas, responderlas y conciliarlas entre pagador y prestador. | N12: «El prestador debe aceptarlas todas para…» renuncia a derechos económicos del hospital; «Las glosas solo se discuten ante…» omite la etapa administrativa previa de respuesta y conciliación. | O12: Decreto 780 de 2016, (Decreto Único Reglamentario del Sector Salud); Resolución 3047 de 2008 y sus modificaciones | P12: SI | Q12: Basica | R12: repaso
... A115: F0114 | B115: PS 2782 de 2026 - ESE 2 - HUHMP Neiva | C115: Regimen disciplinario y CPACA | D115: Técnico | E115: C038 | F115: Caso 038 | G115: Un ciudadano radica una petición y la dependencia competente no responde dentro del término legal. | H115: La petición incompleta debe: | I115: Rechazarse de plano | J115: Requerirse al peticionario para que la complete, con las consecuencias legales si no lo hace | K115: Archivarse sin aviso | L115: b | M115: El artículo 17 del CPACA ordena requerir al peticionario para completar la petición, con desistimiento tácito si no atiende el requerimiento. | N115: «Rechazarse de plano» y «Archivarse sin aviso» niegan el derecho de petición sin agotar el requerimiento previo. | O115: Ley 1437 de 2011, art. 17 | P115: SI | Q115: Basica | R115: repaso
A116: F0115 | B116: PS 2782 de 2026 - ESE 2 - HUHMP Neiva | C116: Precision juridica del verbo | D116: Profesional | E116: C039 | F116: Caso 039 | G116: En la revisión de un proyecto de acto administrativo, la asesora observa que el documento usa indistintamente los verbos notificar, comunicar y publicar, y en otro aparte confunde revocar con anular. | H116: La diferencia correcta entre notificar, comunicar y publicar es: | I116: Notificar los actos particulares, comunicar los de trámite y publicar los generales | J116: Publicar los actos particulares, notificar los de trámite y comunicar los generales | K116: Comunicar los actos particulares, publicar los de trámite y notificar los generales | L116: a | M116: La notificación se reserva a los actos particulares y concretos, la comunicación a actos de trámite o a terceros interesados y la publicación a los actos de carácter general. | N116: «Publicar los actos particulares, notificar los…» y «Comunicar los actos particulares, publicar los…» intercambian los destinatarios: notificar es para los actos particulares, comunicar para los de trámite y publicar para los generales. | O116: Ley 1437 de 2011, arts. 65, 67 y 68 | P116: SI | Q116: Alta
A117: F0116 | B117: PS 2782 de 2026 - ESE 2 - HUHMP Neiva | C117: Precision juridica del verbo | D117: Profesional | E117: C039 | F117: Caso 039 | G117: En la revisión de un proyecto de acto administrativo, la asesora observa que el documento usa indistintamente los verbos notificar, comunicar y publicar, y en otro aparte confunde revocar con anular. | H117: Revocar, anular y suspender se distinguen porque: | I117: Revoca el juez, anula la administración y suspende el superior jerárquico | J117: Revoca la administración, anula el juez y suspende quien tenga competencia | K117: Revoca el superior, anula el Ministerio Público y suspende el ordenador | L117: b | M117: La revocatoria directa es una potestad de la administración, la nulidad la declara el juez y la suspensión es una medida temporal que adopta quien tiene competencia para ello. | N117: «Revoca el juez, anula la administración…» y «Revoca el superior, anula el Ministerio…» reparten los tres verbos entre autoridades distintas de las que el ordenamiento habilita para cada actuación. | O117: Ley 1437 de 2011, arts. 93 y ss.; art. 137 | P117: SI | Q117: Alta
A118: F0117 | B118: PS 2782 de 2026 - ESE 2 - HUHMP Neiva | C118: Precision juridica del verbo | D118: Profesional | E118: C039 | F118: Caso 039 | G118: En la revisión de un proyecto de acto administrativo, la asesora observa que el documento usa indistintamente los verbos notificar, comunicar y publicar, y en otro aparte confunde revocar con anular. | H118: Citar y convocar se diferencian en que: | I118: Se cita a un cuerpo colegiado y se convoca a una persona determinada | J118: Se cita a una persona determinada y se convoca a un cuerpo colegiado | K118: Se cita mediante aviso público y se convoca mediante oficio personal | L118: b | M118: La citación se dirige a una persona determinada para una actuación concreta, mientras la convocatoria llama a un colegiado o a un conjunto de destinatarios. | N118: «Se cita a un cuerpo colegiado…» invierte los destinatarios de cada verbo y «Se cita mediante aviso público y…» los distingue por el medio de comunicación, que no es el criterio. | O118: Ley 1437 de 2011; Ley 909 de 2004, art. 31 | P118: SI | Q118: Alta
A119: F0118 | B119: PS 2782 de 2026 - ESE 2 - HUHMP Neiva | C119: Precision juridica del verbo | D119: Técnico | E119: C040 | F119: Caso 040 | G119: En una minuta institucional aparecen las expresiones derogar, modificar y subrogar, y el equipo necesita usarlas correctamente al actualizar un manual. | H119: Derogar una norma significa: | I119: Dejarla sin efectos hacia el futuro por otra norma de igual rango | J119: Dejarla sin efectos por decisión judicial que declara su nulidad | K119: Dejarla sin aplicación temporal mientras se resuelve el fondo | L119: a | M119: La derogación priva de efectos a la norma hacia el futuro y proviene de otra norma de igual o superior jerarquía. | N119: «Dejarla sin efectos por decisión judicial…» corresponde al control judicial y la «Dejarla sin aplicación temporal mientras se…» a una medida temporal que no extingue la norma. | O119: Ley 153 de 1887; C.P. art. 150 | P119: SI | Q119: Alta
A120: F0119 | B120: PS 2782 de 2026 - ESE 2 - HUHMP Neiva | C120: Precision juridica del verbo | D120: Técnico | E120: C040 | F120: Caso 040 | G120: En una minuta institucional aparecen las expresiones derogar, modificar y subrogar, y el equipo necesita usarlas correctamente al actualizar un manual. | H120: Modificar y subrogar se diferencian en que: | I120: Modificar cambia una parte y subrogar sustituye toda la disposición | J120: Modificar sustituye toda la disposición y subrogar cambia una parte | K120: Modificar deroga la disposición y subrogar suspende su aplicación | L120: a | M120: La modificación cambia una parte del texto y la subrogación sustituye integralmente la disposición por una nueva. | N120: «Modificar sustituye toda la disposición y…» invierte el alcance de los dos verbos y «Modificar deroga la disposición y subrogar…» los confunde con la derogatoria y la suspensión. | O120: Ley 153 de 1887 | P120: SI | Q120: Alta
A121: F0120 | B121: PS 2782 de 2026 - ESE 2 - HUHMP Neiva | C121: Precision juridica del verbo | D121: Técnico | E121: C040 | F121: Caso 040 | G121: En una minuta institucional aparecen las expresiones derogar, modificar y subrogar, y el equipo necesita usarlas correctamente al actualizar un manual. | H121: Una norma revocada antes de entrar a producir efectos, como ocurrió con la Resolución 1732 de 2026: | I121: La norma anterior continúa vigente, sin interrupción de su aplicación | J121: La norma anterior queda derogada y el vacío lo llena la costumbre | K121: La norma anterior revive con efectos retroactivos a la derogatoria | L121: a | M121: Al revocarse íntegramente la resolución que derogaba la norma anterior, esta continúa vigente sin interrupción, como ocurrió con la Resolución 3100 de 2019. | N121: «La norma anterior queda derogada y…» y «La norma anterior revive con efectos…» suponen efectos que la revocatoria no produce. | O121: Resolución 2080 de 2026 (Minsalud); Ley 1437 de 2011, art. 93 | P121: SI | Q121: Alta
A122: F0121 | B122: PS 2782 de 2026 - ESE 2 - HUHMP Neiva | C122: Precision juridica del verbo | D122: Profesional | E122: C041 | F122: Caso 041 | G122: Un usuario interpone recurso de reposición contra una decisión del hospital. El jefe jurídico pregunta con qué verbo debe redactarse la parte resolutiva del acto que resuelve el recurso. | H122: Al resolver el recurso, la autoridad puede: | I122: Derogar, subrogar o adicionar la decisión recurrida | J122: Anular, suspender o inaplicar la decisión recurrida | K122: Confirmar, modificar o revocar la decisión recurrida | L122: c | M122: El artículo 80 del CPACA dispone que al decidir los recursos se resuelve sobre las peticiones, confirmando, modificando o revocando la decisión. | N122: «Anular, suspender o inaplicar la decisión…» usa verbos del control judicial y de las medidas cautelares, que no corresponden a la autoridad que resuelve el recurso; «Derogar, subrogar o adicionar la decisión…» usa verbos propios de la técnica normativa aplicable a normas, no a actos administrativos particulares. | O122: Ley 1437 de 2011, art. 80 | P122: SI | Q122: Alta
A123: F0122 | B123: PS 2782 de 2026 - ESE 2 - HUHMP Neiva | C123: Precision juridica del verbo | D123: Profesional | E123: C041 | F123: Caso 041 | G123: Un usuario interpone recurso de reposición contra una decisión del hospital. El jefe jurídico pregunta con qué verbo debe redactarse la parte resolutiva del acto que resuelve el recurso. | H123: Si la decisión recurrida creó una situación jurídica particular y la administración quiere dejarla sin efectos por fuera del recurso, debe: | I123: Anularla por acto motivado y comunicarlo al titular de la situación | J123: Suspenderla y abrir un nuevo estudio del caso por la administración | K123: Revocarla con el consentimiento expreso y escrito del titular | L123: c | M123: La revocatoria directa de actos de contenido particular y concreto exige el consentimiento previo, expreso y escrito del titular, salvo las excepciones legales. | N123: «Anularla por acto motivado y comunicarlo…» atribuye a la administración un verbo que corresponde al juez; «Suspenderla y abrir un nuevo estudio…» usa una medida temporal que no extingue el acto ni sustituye la revocatoria. | O123: Ley 1437 de 2011, arts. 93 y 97 | P123: SI | Q123: Alta
A124: F0123 | B124: PS 2782 de 2026 - ESE 2 - HUHMP Neiva | C124: Precision juridica del verbo | D124: Profesional | E124: C041 | F124: Caso 041 | G124: Un usuario interpone recurso de reposición contra una decisión del hospital. El jefe jurídico pregunta con qué verbo debe redactarse la parte resolutiva del acto que resuelve el recurso. | H124: El ciudadano quiere que un juez deje sin efectos el acto. El verbo técnicamente correcto en su demanda es: | I124: Solicitar que la administración revoque el acto y lo sustituya por otro | J124: Solicitar la nulidad del acto y el restablecimiento del derecho | K124: Solicitar que el superior derogue el acto y expida uno nuevo | L124: b | M124: Ante la jurisdicción se pide la declaratoria de nulidad del acto y el restablecimiento del derecho; la revocatoria es potestad de la administración. | N124: «Solicitar que la administración revoque el…» pide a un juez una actuación administrativa; «Solicitar que el superior derogue el…» emplea un verbo reservado a las normas, no a los actos administrativos. | O124: Ley 1437 de 2011, art. 138 | P124: SI | Q124: Alta
A125: F0124 | B125: PS 2782 de 2026 - ESE 2 - HUHMP Neiva | C125: Precision juridica del verbo | D125: Profesional | E125: C042 | F125: Caso 042 | G125: En el proceso de selección, el equipo de talento humano redacta comunicaciones sobre los resultados y usa indistintamente los verbos inadmitir, excluir y declarar desierto. | H125: Al aspirante que no acredita los requisitos mínimos del empleo se le debe: | I125: Declararlo desierto, por no proveerse el empleo ofertado | J125: Excluirlo, por incurrir en una causal prevista en el acuerdo | K125: Inadmitirlo, por no acreditar los requisitos mínimos del empleo | L125: c | M125: En la Verificación de Requisitos Mínimos el aspirante que no acredita los requisitos resulta inadmitido y no continúa en el proceso. | N125: «Excluirlo, por incurrir en una causal…» corresponde a quien incurre en causales como el fraude o la suplantación; «Declararlo desierto, por no proveerse el…» se predica del empleo sin inscritos, no del aspirante. | O125: Acuerdo CNSC N° 36 de 2026, art. 13; Anexo Técnico E.S.E. 2 | P125: SI | Q125: Basica
A126: F0125 | B126: PS 2782 de 2026 - ESE 2 - HUHMP Neiva | C126: Precision juridica del verbo | D126: Profesional | E126: C042 | F126: Caso 042 | G126: En el proceso de selección, el equipo de talento humano redacta comunicaciones sobre los resultados y usa indistintamente los verbos inadmitir, excluir y declarar desierto. | H126: Al aspirante que aporta un documento falso se le debe: | I126: Inadmitirlo en la verificación de requisitos mínimos del empleo | J126: Excluirlo en cualquier momento en que se compruebe el hecho | K126: Retirarlo de la lista de elegibles una vez esta se conforme | L126: b | M126: Aportar documentos falsos o adulterados es causal de exclusión, aplicable en cualquier etapa del proceso en que se compruebe. | N126: «Inadmitirlo en la verificación de requisitos…» usa el verbo de la VRM para una conducta sancionable; «Retirarlo de la lista de elegibles…» limita el efecto a una etapa final cuando la causal opera en cualquier momento. | O126: Acuerdo CNSC N° 36 de 2026, art. 7 | P126: SI | Q126: Basica
A127: F0126 | B127: PS 2782 de 2026 - ESE 2 - HUHMP Neiva | C127: Precision juridica del verbo | D127: Profesional | E127: C042 | F127: Caso 042 | G127: En el proceso de selección, el equipo de talento humano redacta comunicaciones sobre los resultados y usa indistintamente los verbos inadmitir, excluir y declarar desierto. | H127: Cuando un empleo ofertado en ascenso no registra inscritos, la CNSC debe: | I127: Excluir el empleo de la oferta pública de empleos de carrera | J127: Declararlo desierto y proveerlo en la modalidad de abierto | K127: Inadmitir el empleo y trasladarlo al siguiente proceso | L127: b | M127: Las vacantes de ascenso sin inscritos se declaran desiertas y se proveen mediante el mismo proceso en la modalidad abierto. | N127: «Excluir el empleo de la oferta…» y «Inadmitir el empleo y trasladarlo al…» aplican a aspirantes, no a vacantes: el verbo cambia según recaiga sobre la persona o sobre el empleo. | O127: Ley 1960 de 2019, art. 2; Acuerdo CNSC N° 36 de 2026, art. 3 | P127: SI | Q127: Basica
... A157: F0156 | B157: PS 2782 de 2026 - ESE 2 - HUHMP Neiva | C157: Precision juridica del verbo | D157: Técnico | E157: C052 | F157: Caso 052 | G157: Un auditor sanitario visita el hospital y debe describir correctamente las medidas que puede adoptar la autoridad. | H157: Terminado el procedimiento administrativo sancionatorio, la autoridad puede: | I157: Adoptar una medida sanitaria de seguridad como sanción | J157: Imponer la sanción mediante acto motivado | K157: Suspender el procedimiento | L157: b | M157: La sanción se impone mediante acto administrativo motivado al término del procedimiento sancionatorio. | N157: «Adoptar una medida sanitaria de seguridad…» usa como sanción una medida preventiva; «Suspender el procedimiento» describe una decisión procesal, no el resultado del procedimiento. | O157: Ley 1437 de 2011, arts. 47 a 50 | P157: SI | Q157: Alta
A158: F0157 | B158: PS 2782 de 2026 - ESE 2 - HUHMP Neiva | C158: Sistema de salud y Ley 100 de 1993 | D158: Profesional | E158: C053 | F158: Caso 053 | G158: La oficina de planeación revisa cómo se financia la operación del hospital y cuál es el papel de cada actor del sistema. | H158: La UPC es: | I158: El valor anual que reconoce el sistema por cada afiliado para financiar el plan de beneficios | J158: La tarifa que cobra la IPS por cada atención | K158: El copago que paga el usuario | L158: a | M158: La Unidad de Pago por Capitación es el valor anual reconocido por afiliado para financiar el plan de beneficios. | N158: «La tarifa que cobra la IPS…» describe la tarifa contractual del prestador y «El copago que paga el usuario» un pago moderador a cargo del usuario. | O158: Ley 100 de 1993, art. 182 | P158: SI | Q158: Basica | R158: repaso
A159: F0158 | B159: PS 2782 de 2026 - ESE 2 - HUHMP Neiva | C159: Sistema de salud y Ley 100 de 1993 | D159: Profesional | E159: C053 | F159: Caso 053 | G159: La oficina de planeación revisa cómo se financia la operación del hospital y cuál es el papel de cada actor del sistema. | H159: La ADRES cumple la función de: | I159: Administrar los recursos del sistema general de seguridad social en salud | J159: Habilitar los servicios de salud | K159: Vigilar a los prestadores | L159: a | M159: La ADRES administra los recursos del sistema y realiza los reconocimientos y giros que le competen. | N159: «Habilitar los servicios de salud» corresponde a las entidades territoriales y «Vigilar a los prestadores» a la Superintendencia Nacional de Salud. | O159: Ley 1753 de 2015, art. 66 | P159: SI | Q159: Basica | R159: repaso
A160: F0159 | B160: PS 2782 de 2026 - ESE 2 - HUHMP Neiva | C160: Sistema de salud y Ley 100 de 1993 | D160: Profesional | E160: C053 | F160: Caso 053 | G160: La oficina de planeación revisa cómo se financia la operación del hospital y cuál es el papel de cada actor del sistema. | H160: La afiliación al sistema es: | I160: Optativa si la persona tiene medicina prepagada | J160: Voluntaria para trabajadores independientes | K160: Obligatoria para todos los residentes en Colombia | L160: c | M160: La afiliación al SGSSS es obligatoria para todos los residentes en el país. | N160: «Voluntaria para trabajadores independientes» y «Optativa si la persona tiene medicina…» crean excepciones que la ley no contempla; la prepagada es complementaria, no sustituye la afiliación. | O160: Ley 100 de 1993, art. 153 | P160: SI | Q160: Basica | R160: repaso
A161: F0160 | B161: PS 2782 de 2026 - ESE 2 - HUHMP Neiva | C161: Sistema de salud y Ley 100 de 1993 | D161: Profesional | E161: C054 | F161: Caso 054 | G161: El comité financiero analiza la relación contractual entre el hospital y las EPS. | H161: El acuerdo de voluntades entre EPS e IPS debe contener como mínimo: | I161: Solo el valor total del contrato | J161: Objeto, población, servicios, tarifas, mecanismos de pago y vigencia | K161: Solo las tarifas de los procedimientos | L161: b | M161: Los acuerdos de voluntades deben precisar objeto, población, servicios contratados, tarifas, mecanismo de pago y vigencia. | N161: «Solo el valor total del contrato» y «Solo las tarifas de los procedimientos» omiten elementos esenciales sin los cuales el acuerdo es indeterminado. | O161: Decreto 780 de 2016, (Decreto Único Reglamentario del Sector Salud); Resolución 3047 de 2008 | P161: SI | Q161: Basica | R161: repaso
A162: F0161 | B162: PS 2782 de 2026 - ESE 2 - HUHMP Neiva | C162: Sistema de salud y Ley 100 de 1993 | D162: Profesional | E162: C054 | F162: Caso 054 | G162: El comité financiero analiza la relación contractual entre el hospital y las EPS. | H162: El mecanismo de pago por capitación implica que: | I162: El prestador recibe un valor fijo por persona y período, asumiendo el riesgo de la demanda | J162: Se paga cada actividad realizada | K162: Se paga por caso o conjunto de atenciones | L162: a | M162: En la capitación se paga un valor fijo por persona y período, trasladando parte del riesgo al prestador. | N162: «Se paga cada actividad realizada» describe el pago por evento y «Se paga por caso o conjunto…» el pago global prospectivo o por paquete. | O162: Decreto 780 de 2016, (Decreto Único Reglamentario del Sector Salud) | P162: SI | Q162: Basica | R162: repaso
A163: F0162 | B163: PS 2782 de 2026 - ESE 2 - HUHMP Neiva | C163: Sistema de salud y Ley 100 de 1993 | D163: Profesional | E163: C054 | F163: Caso 054 | G163: El comité financiero analiza la relación contractual entre el hospital y las EPS. | H163: La auditoría de cuentas médicas tiene por objeto: | I163: Fijar las tarifas del contrato | J163: Verificar la pertinencia, la calidad y el soporte de los servicios facturados | K163: Sustituir la historia clínica | L163: b | M163: La auditoría verifica pertinencia, calidad y soportes de lo facturado frente a lo pactado. | N163: «Fijar las tarifas del contrato» es materia de negociación contractual y «Sustituir la historia clínica» confunde auditoría con registro clínico. | O163: Decreto 780 de 2016, (Decreto Único Reglamentario del Sector Salud) | P163: SI | Q163: Basica | R163: repaso
A164: F0163 | B164: PS 2782 de 2026 - ESE 2 - HUHMP Neiva | C164: Sistema de salud y Ley 100 de 1993 | D164: Técnico | E164: C055 | F164: Caso 055 | G164: Un técnico de admisiones debe explicar el plan de beneficios y las exclusiones a un usuario. | H164: El plan de beneficios en salud con cargo a la UPC: | I164: Cubre lo necesario para la promoción, prevención, diagnóstico, tratamiento y rehabilitación, salvo exclusiones expresas | J164: Cubre solo urgencias | K164: Cubre solo lo que autorice la EPS | L164: a | M164: El plan de beneficios cubre de manera integral los servicios necesarios, salvo lo expresamente excluido. | N164: «Cubre solo urgencias» y «Cubre solo lo que autorice la…» reducen la cobertura legal a una franja mínima o a la voluntad del asegurador. | O164: Ley 1751 de 2015, art. 15; Resolución de PBS vigente | P164: SI | Q164: Basica | R164: repaso
A165: F0164 | B165: PS 2782 de 2026 - ESE 2 - HUHMP Neiva | C165: Sistema de salud y Ley 100 de 1993 | D165: Técnico | E165: C055 | F165: Caso 055 | G165: Un técnico de admisiones debe explicar el plan de beneficios y las exclusiones a un usuario. | H165: Los servicios no financiados con la UPC: | I165: Se gestionan por el mecanismo de prescripción vigente (MIPRES) y su financiación tiene reglas propias | J165: No pueden prestarse | K165: Los paga siempre el usuario | L165: a | M165: Los servicios no financiados con la UPC se prescriben por la herramienta dispuesta para ello y su financiación sigue reglas específicas. | N165: «No pueden prestarse» niega el acceso y «Los paga siempre el usuario» traslada al usuario un costo que la normativa no le asigna. | O165: Decreto 780 de 2016, (Decreto Único Reglamentario del Sector Salud); Resolución 1885 de 2018 | P165: SI | Q165: Basica | R165: repaso
A166: F0165 | B166: PS 2782 de 2026 - ESE 2 - HUHMP Neiva | C166: Sistema de salud y Ley 100 de 1993 | D166: Técnico | E166: C055 | F166: Caso 055 | G166: Un técnico de admisiones debe explicar el plan de beneficios y las exclusiones a un usuario. | H166: La portabilidad permite al afiliado: | I166: Recibir atención en un municipio distinto al de afiliación | J166: Cambiar de EPS cuando quiera sin requisitos | K166: Elegir el prestador que desee a nivel nacional sin restricción | L166: a | M166: La portabilidad garantiza el acceso a los servicios en un municipio distinto al de afiliación. | N166: «Cambiar de EPS cuando quiera sin…» describe el traslado, con reglas de permanencia; «Elegir el prestador que desee a…» excede el derecho de elección dentro de la red. | O166: Decreto 780 de 2016, (Decreto Único Reglamentario del Sector Salud) | P166: SI | Q166: Basica | R166: repaso
A167: F0166 | B167: PS 2782 de 2026 - ESE 2 - HUHMP Neiva | C167: Sistema de salud y Ley 100 de 1993 | D167: Profesional | E167: C056 | F167: Caso 056 | G167: La gerencia evalúa el desempeño de la red pública del departamento. | H167: La rectoría del sistema de salud en el departamento corresponde a: | I167: A la EPS con mayor número de afiliados | J167: La secretaría departamental de salud, en el marco de sus competencias | K167: Al hospital de mayor complejidad | L167: b | M167: La dirección del sector salud en el departamento corresponde a la entidad territorial, conforme a la Ley 715 de 2001. | N167: «A la EPS con mayor número…» y «Al hospital de mayor complejidad» son actores del sistema sin competencia de rectoría territorial. | O167: Ley 715 de 2001, art. 43 | P167: SI | Q167: Basica | R167: repaso
A168: F0167 | B168: PS 2782 de 2026 - ESE 2 - HUHMP Neiva | C168: Sistema de salud y Ley 100 de 1993 | D168: Profesional | E168: C056 | F168: Caso 056 | G168: La gerencia evalúa el desempeño de la red pública del departamento. | H168: La inspección, vigilancia y control del sistema corresponde principalmente a: | I168: La Procuraduría General | J168: La Contraloría General | K168: La Superintendencia Nacional de Salud | L168: c | M168: La Superintendencia Nacional de Salud ejerce la inspección, vigilancia y control sobre los actores del sistema. | N168: «La Contraloría General» ejerce control fiscal y «La Procuraduría General» control disciplinario: ninguno reemplaza la vigilancia sectorial. | O168: Ley 1122 de 2007, art. 35 | P168: SI | Q168: Basica | R168: repaso
A169: F0168 | B169: PS 2782 de 2026 - ESE 2 - HUHMP Neiva | C169: Sistema de salud y Ley 100 de 1993 | D169: Profesional | E169: C056 | F169: Caso 056 | G169: La gerencia evalúa el desempeño de la red pública del departamento. | H169: El hospital de alta complejidad dentro de la red debe: | I169: Rechazar toda remisión de primer nivel | J169: Atender toda consulta que llegue, sea cual sea su complejidad | K169: Atender lo que corresponde a su nivel y devolver al nivel resolutivo lo que no lo requiere | L169: c | M169: La organización en red implica resolver en el nivel que corresponde y contrarreferir lo que puede atenderse en menor complejidad. | N169: «Atender toda consulta que llegue, sea…» satura la alta complejidad y «Rechazar toda remisión de primer nivel» desconoce la obligación de recibir lo pertinente. | O169: Ley 1438 de 2011; Decreto 780 de 2016, (Decreto Único Reglamentario del Sector Salud) | P169: SI | Q169: Basica | R169: repaso
... A334: F0333 | B334: PS 2782 de 2026 - ESE 2 - HUHMP Neiva | C334: Regimen disciplinario y CPACA | D334: Profesional | E334: C111 | F334: Caso 111 | G334: Un servidor pregunta por el régimen de sus deberes y prohibiciones. | H334: La sanción de destitución e inhabilidad general se impone por: | I334: Faltas leves reiteradas | J334: Cualquier falta grave | K334: Faltas gravísimas dolosas o realizadas con culpa gravísima | L334: c | M334: La destitución e inhabilidad general corresponde a faltas gravísimas dolosas o con culpa gravísima. | N334: «Cualquier falta grave» y «Faltas leves reiteradas» aplican una sanción desproporcionada a la calificación de la falta. | O334: Ley 1952 de 2019, art. 48 | P334: SI | Q334: Basica | R334: repaso
A335: F0334 | B335: PS 2782 de 2026 - ESE 2 - HUHMP Neiva | C335: Precision juridica del verbo | D335: Profesional | E335: C112 | F335: Caso 112 | G335: En una minuta se usan indistintamente los verbos de la ejecución del acto. | H335: Cuando la administración lleva a la práctica su propia decisión ejecutoriada, el verbo es: | I335: Ejecutoriar el acto | J335: Ejecutar el acto | K335: Ejecutarse de plano | L335: b | M335: La administración ejecuta el acto en firme; la ejecutoria es la condición que lo habilita. | N335: «Ejecutoriar el acto» nombra la condición, no la acción; «Ejecutarse de plano» no describe la actuación. | O335: Ley 1437 de 2011, art. 89 | P335: SI | Q335: Alta
A336: F0335 | B336: PS 2782 de 2026 - ESE 2 - HUHMP Neiva | C336: Precision juridica del verbo | D336: Profesional | E336: C112 | F336: Caso 112 | G336: En una minuta se usan indistintamente los verbos de la ejecución del acto. | H336: El acto que se cumple sin intervención judicial se apoya en: | I336: El consentimiento expreso del particular destinatario | J336: La orden previa del juez de lo contencioso administrativo | K336: El privilegio de ejecución oficiosa de la administración | L336: c | M336: La administración tiene el privilegio de ejecutar sus propios actos en firme. | N336: «La orden previa del juez de…» y «El consentimiento expreso del particular destinatario» suponen una intervención que la ley no exige. | O336: Ley 1437 de 2011, art. 89 | P336: SI | Q336: Alta
A337: F0336 | B337: PS 2782 de 2026 - ESE 2 - HUHMP Neiva | C337: Precision juridica del verbo | D337: Profesional | E337: C112 | F337: Caso 112 | G337: En una minuta se usan indistintamente los verbos de la ejecución del acto. | H337: Suspender la ejecución de un acto por decisión judicial se denomina: | I337: Derogatoria parcial de los efectos del acto | J337: Revocatoria directa de los efectos del acto | K337: Suspensión provisional de los efectos del acto | L337: c | M337: La suspensión provisional es una medida cautelar del juez sobre los efectos del acto. | N337: «Revocatoria directa de los efectos del…» es potestad administrativa y «Derogatoria parcial de los efectos del…» opera sobre normas. | O337: Ley 1437 de 2011, art. 231 | P337: SI | Q337: Alta
A338: F0337 | B338: PS 2782 de 2026 - ESE 2 - HUHMP Neiva | C338: Precision juridica del verbo | D338: Profesional | E338: C113 | F338: Caso 113 | G338: El comité redacta un acta y discute cómo nombrar sus decisiones. | H338: Cuando el comité aprueba un documento que orienta su gestión interna, el verbo es: | I338: Adoptar | J338: Expedir | K338: Promulgar | L338: a | M338: Los instrumentos de gestión se adoptan mediante la decisión del órgano competente. | N338: «Expedir» se usa para actos administrativos y «Promulgar» para la publicación de leyes. | O338: Ley 1437 de 2011, art. 14: términos para resolver peticiones; Decreto 1499 de 2017 | P338: SI | Q338: Basica
A339: F0338 | B339: PS 2782 de 2026 - ESE 2 - HUHMP Neiva | C339: Precision juridica del verbo | D339: Profesional | E339: C113 | F339: Caso 113 | G339: El comité redacta un acta y discute cómo nombrar sus decisiones. | H339: Cuando la junta directiva produce un acuerdo, el verbo correcto es: | I339: Expedir el acuerdo | J339: Sancionar el acuerdo | K339: Proferir el acuerdo | L339: a | M339: Los órganos administrativos expiden los actos de su competencia. | N339: «Sancionar el acuerdo» corresponde al trámite de las leyes y «Proferir el acuerdo» a las decisiones judiciales. | O339: Decreto 1876 de 1994 | P339: SI | Q339: Basica
A340: F0339 | B340: PS 2782 de 2026 - ESE 2 - HUHMP Neiva | C340: Precision juridica del verbo | D340: Profesional | E340: C113 | F340: Caso 113 | G340: El comité redacta un acta y discute cómo nombrar sus decisiones. | H340: Cuando se deja constancia de lo ocurrido en la sesión, el verbo es: | I340: Certificar la sesión | J340: Consignar en el acta | K340: Protocolizar la sesión | L340: b | M340: Lo ocurrido se consigna en el acta; certificar y protocolizar son actos distintos y posteriores. | N340: «Certificar la sesión» supone dar fe de un hecho y «Protocolizar la sesión» elevar a escritura pública. | O340: Ley 1437 de 2011, art. 14: términos para resolver peticiones | P340: SI | Q340: Basica
A341: F0340 | B341: PS 2782 de 2026 - ESE 2 - HUHMP Neiva | C341: Precision juridica del verbo | D341: Técnico | E341: C114 | F341: Caso 114 | G341: En la ventanilla se confunden los verbos del trámite de peticiones. | H341: Cuando la entidad pide al ciudadano completar su solicitud, el verbo es: | I341: Requerir | J341: Notificar | K341: Emplazar | L341: a | M341: La entidad requiere al peticionario para completar la solicitud. | N341: «Notificar» es dar a conocer una decisión y «Emplazar» un llamado público. | O341: Ley 1437 de 2011, art. 17 | P341: SI | Q341: Basica
A342: F0341 | B342: PS 2782 de 2026 - ESE 2 - HUHMP Neiva | C342: Precision juridica del verbo | D342: Técnico | E342: C114 | F342: Caso 114 | G342: En la ventanilla se confunden los verbos del trámite de peticiones. | H342: Cuando el ciudadano no responde el requerimiento, se produce: | I342: La caducidad de la acción frente a la entidad | J342: El desistimiento tácito de la petición presentada | K342: La revocatoria del trámite iniciado por la entidad | L342: b | M342: Vencido el término sin respuesta se declara el desistimiento tácito. | N342: «La caducidad de la acción frente…» y «La revocatoria del trámite iniciado por…» nombran figuras ajenas a este trámite. | O342: Ley 1437 de 2011, art. 17 | P342: SI | Q342: Basica
A343: F0342 | B343: PS 2782 de 2026 - ESE 2 - HUHMP Neiva | C343: Precision juridica del verbo | D343: Técnico | E343: C114 | F343: Caso 114 | G343: En la ventanilla se confunden los verbos del trámite de peticiones. | H343: Cuando la entidad traslada la petición por competencia, el verbo es: | I343: Remitir | J343: Devolver | K343: Archivar | L343: a | M343: La petición se remite a la autoridad competente, informando al interesado. | N343: «Devolver» y «Archivar» dejan la petición sin trámite. | O343: Ley 1437 de 2011, art. 21 | P343: SI | Q343: Basica
A344: F0343 | B344: PS 2782 de 2026 - ESE 2 - HUHMP Neiva | C344: Precision juridica del verbo | D344: Profesional | E344: C115 | F344: Caso 115 | G344: En un informe técnico se confunden los verbos de la evaluación. | H344: Cuando se comprueba que un documento cumple un requisito, el verbo es: | I344: Verificar el dato | J344: Valorar según criterio | K344: Ponderar conforme al peso | L344: a | M344: La verificación comprueba el cumplimiento de un requisito; la valoración asigna puntaje. | N344: «Valorar» implica calificar y «Ponderar» asignar pesos relativos. | O344: Acuerdo CNSC N° 36 de 2026; Anexo Técnico | P344: SI | Q344: Basica
A345: F0344 | B345: PS 2782 de 2026 - ESE 2 - HUHMP Neiva | C345: Precision juridica del verbo | D345: Profesional | E345: C115 | F345: Caso 115 | G345: En un informe técnico se confunden los verbos de la evaluación. | H345: Cuando se asigna puntaje a la educación adicional, el verbo es: | I345: Homologar | J345: Verificar | K345: Valorar | L345: c | M345: La prueba de valoración de antecedentes asigna puntaje a lo adicional al requisito mínimo. | N345: «Verificar» es la etapa previa de VRM y «Homologar» supone equivalencia entre títulos. | O345: Anexo Técnico E.S.E. 2 | P345: SI | Q345: Basica
A346: F0345 | B346: PS 2782 de 2026 - ESE 2 - HUHMP Neiva | C346: Precision juridica del verbo | D346: Profesional | E346: C115 | F346: Caso 115 | G346: En un informe técnico se confunden los verbos de la evaluación. | H346: Cuando se aplica una equivalencia entre estudios y experiencia, el verbo es: | I346: Homologar | J346: Valorar | K346: Certificar | L346: a | M346: La homologación aplica equivalencias previstas en el manual de funciones, solo en la VRM. | N346: «Valorar» corresponde a la prueba clasificatoria y «Certificar» a la expedición de una constancia. | O346: Anexo Técnico E.S.E. 2; Decreto 785 de 2005 | P346: SI | Q346: Basica
... A361: F0360 | B361: PS 2782 de 2026 - ESE 2 - HUHMP Neiva | C361: Precision juridica del verbo | D361: Técnico | E361: C120 | F361: Caso 120 | G361: En el proceso de selección se confunden los verbos de la lista de elegibles. | H361: Cuando la lista se usa en orden descendente por retiro de un elegible, el fenómeno es: | I361: La modificación de la lista | J361: La movilidad de la lista | K361: La firmeza de la lista | L361: b | M361: La movilidad permite usar la lista en orden descendente sin nuevo acto administrativo. | N361: «La modificación de la lista» supone adicionar o reubicar por error y «La firmeza de la lista» alude a sus efectos jurídicos. | O361: Acuerdo CNSC N° 36 de 2026, art. 31 | P361: SI | Q361: Alta
A362: F0361 | B362: PS 2782 de 2026 - ESE 2 - HUHMP Neiva | C362: Urgencias | D362: Profesional | E362: C121 | F362: Caso 121 | G362: Una mujer de 34 años con lupus y compromiso renal ingresa a urgencias el 12 de enero a las 21:40 por deterioro de su función renal. El 13 de enero el médico tratante solicita por escrito a la EPS el traslado a una institución con nefrología y unidad de cuidados intensivos, servicios que el hospital no tiene habilitados. Entre el 17 y el 25 de enero la solicitud se reitera ocho veces, advirtiendo alto riesgo de complicaciones. La EPS no responde y ninguna institución acepta la remisión. Usted coordina el servicio. | H362: ¿Cuál es su actuación prioritaria en este momento? | I362: Dar de alta con orden de control prioritario por nefrología y entregar la epicrisis | J362: Sostener la atención, activar el centro regulador y dejar constancia de cada gestión | K362: Trasladar a la paciente a la institución más cercana e informar al receptor en el trayecto | L362: b | M362: La continuidad obliga a mantener la atención hasta que exista un destino asistencial seguro, y el centro regulador es la instancia que coordina la asignación del receptor. | N362: Dar de alta interrumpe el manejo de una paciente que sigue requiriendo nefrología; trasladar sin receptor aceptado la expone durante el viaje. | O362: Ley 1751 de 2015, art. 6; Resolución 1220 de 2010; Corte Constitucional, Sentencia T-573 de 2023 | P362: SI | Q362: Alta | R362: v2
A363: F0362 | B363: PS 2782 de 2026 - ESE 2 - HUHMP Neiva | C363: Urgencias | D363: Profesional | E363: C121 | F363: Caso 121 | G363: Una mujer de 34 años con lupus y compromiso renal ingresa a urgencias el 12 de enero a las 21:40 por deterioro de su función renal. El 13 de enero el médico tratante solicita por escrito a la EPS el traslado a una institución con nefrología y unidad de cuidados intensivos, servicios que el hospital no tiene habilitados. Entre el 17 y el 25 de enero la solicitud se reitera ocho veces, advirtiendo alto riesgo de complicaciones. La EPS no responde y ninguna institución acepta la remisión. Usted coordina el servicio. | H363: ¿Qué documento soporta que el hospital sí gestionó el traslado? | I363: La bitácora de remisión con fecha, hora, destinatario y respuesta de cada solicitud | J363: El contrato vigente con la EPS y el manual de tarifas aplicable al servicio prestado | K363: La epicrisis firmada por el médico tratante en el momento del egreso de la paciente | L363: a | M363: La bitácora de remisión es el registro que acredita la trazabilidad de cada gestión, su destinatario y la respuesta obtenida. | N363: «El contrato vigente con la EPS…» prueba la relación contractual, no la gestión del caso; «La epicrisis firmada por el médico…» documenta el egreso, que es un momento posterior y distinto al de las gestiones. | O363: Resolución 3047 de 2008; Resolución 1220 de 2010 | P363: SI | Q363: Alta | R363: v2
A364: F0363 | B364: PS 2782 de 2026 - ESE 2 - HUHMP Neiva | C364: Urgencias | D364: Profesional | E364: C121 | F364: Caso 121 | G364: Una mujer de 34 años con lupus y compromiso renal ingresa a urgencias el 12 de enero a las 21:40 por deterioro de su función renal. El 13 de enero el médico tratante solicita por escrito a la EPS el traslado a una institución con nefrología y unidad de cuidados intensivos, servicios que el hospital no tiene habilitados. Entre el 17 y el 25 de enero la solicitud se reitera ocho veces, advirtiendo alto riesgo de complicaciones. La EPS no responde y ninguna institución acepta la remisión. Usted coordina el servicio. | H364: Una institución de alta complejidad niega la recepción porque no tiene convenio con la EPS de la paciente. Esa negativa: | I364: Constituye una barrera administrativa: la atención de urgencias no depende del convenio | J364: Es válida mientras no exista convenio, porque sin él la receptora no puede facturar | K364: Es válida si la EPS no autoriza el ingreso por escrito antes de que llegue el paciente | L364: a | M364: La atención inicial de urgencias es obligatoria para todo prestador y no puede condicionarse a convenio, autorización ni pago previo. | N364: El convenio y la autorización son asuntos entre entidades; ninguno condiciona una atención que la ley define como incondicionada. | O364: Ley 1751 de 2015, art. 14; Corte Constitucional, Sentencia T-573 de 2023 | P364: SI | Q364: Alta | R364: v2
A365: F0364 | B365: PS 2782 de 2026 - ESE 2 - HUHMP Neiva | C365: Urgencias | D365: Profesional | E365: C122 | F365: Caso 122 | G365: Una mujer venezolana en situación migratoria irregular, sin afiliación al sistema, es atendida en urgencias por una complicación obstétrica el 3 de marzo. Superada la fase inicial, el médico tratante prescribe estudios y un procedimiento que el hospital sí tiene habilitados. Facturación advierte que no hay quién pague y propone suspender el plan de manejo hasta definir el responsable. La usuaria no tiene documento de identidad colombiano. | H365: Frente a la propuesta de facturación, su decisión debe ser: | I365: Suspender los estudios prescritos y esperar la confirmación escrita del pago | J365: Continuar el plan de manejo y tramitar en paralelo la ruta de pago | K365: Entregar a la usuaria las órdenes y orientarla hacia la red privada | L365: b | M365: La condición migratoria o de aseguramiento no habilita a interrumpir una atención en curso; la definición del pagador es un trámite administrativo paralelo. | N365: «Suspender los estudios prescritos y esperar…» condiciona la atención a un trámite económico y «Entregar a la usuaria las órdenes…» traslada a la usuaria una carga que el prestador no puede imponerle en esa condición clínica. | O365: Ley 1751 de 2015, arts. 6 y 14; Corte Constitucional, Sentencia T-254 de 2021 | P365: SI | Q365: Alta | R365: v2
A366: F0365 | B366: PS 2782 de 2026 - ESE 2 - HUHMP Neiva | C366: Urgencias | D366: Profesional | E366: C122 | F366: Caso 122 | G366: Una mujer venezolana en situación migratoria irregular, sin afiliación al sistema, es atendida en urgencias por una complicación obstétrica el 3 de marzo. Superada la fase inicial, el médico tratante prescribe estudios y un procedimiento que el hospital sí tiene habilitados. Facturación advierte que no hay quién pague y propone suspender el plan de manejo hasta definir el responsable. La usuaria no tiene documento de identidad colombiano. | H366: La exigencia del documento de identidad colombiano como condición para la atención: | I366: Procede si la usuaria no acredita afiliación ni capacidad de pago al momento del ingreso | J366: No procede: la identificación se gestiona sin interrumpir ni aplazar la atención | K366: Procede, para registrar la atención en los sistemas de información del prestador | L366: b | M366: La identificación del usuario es un trámite administrativo que se resuelve durante o después de la atención, nunca como condición para prestarla. | N366: Registrar y verificar el aseguramiento son trámites administrativos que se resuelven durante o después de la atención, nunca antes. | O366: Ley 1751 de 2015, art. 14; Decreto 780 de 2016 | P366: SI | Q366: Alta | R366: v2
A367: F0366 | B367: PS 2782 de 2026 - ESE 2 - HUHMP Neiva | C367: Urgencias | D367: Profesional | E367: C122 | F367: Caso 122 | G367: Una mujer venezolana en situación migratoria irregular, sin afiliación al sistema, es atendida en urgencias por una complicación obstétrica el 3 de marzo. Superada la fase inicial, el médico tratante prescribe estudios y un procedimiento que el hospital sí tiene habilitados. Facturación advierte que no hay quién pague y propone suspender el plan de manejo hasta definir el responsable. La usuaria no tiene documento de identidad colombiano. | H367: ¿A quién corresponde, en principio, la financiación de esa atención? | I367: Al hospital, que debe asumirla dentro de su responsabilidad social institucional | J367: A la entidad territorial, con los recursos para la población pobre no asegurada | K367: A la usuaria, mediante acuerdo de pago suscrito antes de continuar el tratamiento | L367: b | M367: La atención de la población pobre no asegurada se financia con los recursos que administra la entidad territorial, conforme a la distribución de competencias del sector. | N367: Cargar el costo al hospital desconoce la fuente que la ley previó, y cobrarle a la usuaria convierte la atención en una transacción particular. | O367: Ley 715 de 2001, art. 43; Decreto 780 de 2016; Corte Constitucional, Sentencia T-254 de 2021 | P367: SI | Q367: Alta | R367: v2
A368: F0367 | B368: PS 2782 de 2026 - ESE 2 - HUHMP Neiva | C368: Referencia y contrarreferencia | D368: Profesional | E368: C123 | F368: Caso 123 | G368: Un paciente de un municipio del sur del Huila es remitido al hospital universitario para un control ambulatorio prioritario por nefrología. La familia informa que vive de jornales, que el viaje cuesta más de lo que gana en una semana y que si no viaja el paciente perderá el control. La EPS responde que el desplazamiento corre por cuenta del usuario. El paciente no está hospitalizado y su condición no es de urgencia. | H368: Conforme a la regla general sobre gastos de desplazamiento en remisiones: | I368: Corren por cuenta del usuario, salvo urgencia o paciente internado que requiera más | J368: Corren por cuenta del prestador que remite, conforme a la continuidad | K368: Corren por cuenta de la entidad territorial cuando el municipio no ofrece el servicio | L368: a | M368: La regla general asigna el desplazamiento al usuario, con las excepciones de urgencia certificada y paciente internado que requiere atención complementaria. | N368: Las dos primeras trasladan el costo a actores distintos de los que la norma señala para la regla general. | O368: Decreto 780 de 2016; Resolución 5261 de 1994, art. 2, parágrafo | P368: SI | Q368: Media | R368: v2
A369: F0368 | B369: PS 2782 de 2026 - ESE 2 - HUHMP Neiva | C369: Referencia y contrarreferencia | D369: Profesional | E369: C123 | F369: Caso 123 | G369: Un paciente de un municipio del sur del Huila es remitido al hospital universitario para un control ambulatorio prioritario por nefrología. La familia informa que vive de jornales, que el viaje cuesta más de lo que gana en una semana y que si no viaja el paciente perderá el control. La EPS responde que el desplazamiento corre por cuenta del usuario. El paciente no está hospitalizado y su condición no es de urgencia. | H369: La jurisprudencia admite una excepción a esa regla cuando concurren: | I369: La falta de recursos de la familia y el riesgo de no realizar el viaje | J369: La condición de especial protección y una orden de control prioritario vigente | K369: La distancia de más de cien kilómetros y la falta de transporte al destino | L369: a | M369: La Corte ha fijado dos requisitos concurrentes: la insuficiencia económica del paciente y su familia, y el riesgo derivado de no realizar el traslado. | N369: Los criterios de distancia y de categoría del paciente no son los dos requisitos concurrentes que fijó la jurisprudencia. | O369: Corte Constitucional, Sentencias T-252 de 2007 y T-1129 de 2008 | P369: SI | Q369: Media | R369: v2
A370: F0369 | B370: PS 2782 de 2026 - ESE 2 - HUHMP Neiva | C370: Referencia y contrarreferencia | D370: Profesional | E370: C123 | F370: Caso 123 | G370: Un paciente de un municipio del sur del Huila es remitido al hospital universitario para un control ambulatorio prioritario por nefrología. La familia informa que vive de jornales, que el viaje cuesta más de lo que gana en una semana y que si no viaja el paciente perderá el control. La EPS responde que el desplazamiento corre por cuenta del usuario. El paciente no está hospitalizado y su condición no es de urgencia. | H370: El paciente requiere acompañante porque depende de un tercero para movilizarse. Frente a los gastos del acompañante: | I370: Pueden reconocerse por el principio de integralidad si el paciente depende de otro | J370: Se niegan, porque el plan de beneficios reconoce gastos respecto del paciente | K370: Se reconocen cuando el acompañante está afiliado a la misma entidad promotora | L370: a | M370: La jurisprudencia ha extendido el reconocimiento al acompañante, con fundamento en el principio de integralidad, cuando el paciente no puede desplazarse por sí mismo. | N370: Negarlos desconoce el desarrollo jurisprudencial, y exigir que el acompañante esté afiliado introduce una condición ajena al criterio. | O370: Ley 1751 de 2015, art. 8; Corte Constitucional, Sentencia T-131 de 2025 | P370: SI | Q370: Media | R370: v2
A371: F0370 | B371: PS 2782 de 2026 - ESE 2 - HUHMP Neiva | C371: Referencia y contrarreferencia | D371: Técnico | E371: C124 | F371: Caso 124 | G371: A las 03:20 ingresa por urgencias un hombre politraumatizado en un accidente de tránsito. El vehículo no tenía póliza del seguro obligatorio vigente. El paciente requiere manejo en una institución de tercer nivel que el hospital no presta. El auxiliar de la oficina de referencia pregunta a quién debe dirigir la solicitud y quién asumirá el costo, porque el conductor asegura que la familia no tiene cómo pagar. | H371: La gestión de la remisión corresponde, en primer lugar, a: | I371: La institución donde se encuentra el paciente, que adelanta la solicitud | J371: La familia del paciente, que busca una institución con camas disponibles | K371: La autoridad de tránsito, que documenta el traslado dentro del informe del accidente | L371: a | M371: La responsabilidad de gestionar la remisión recae en el prestador que tiene al paciente bajo su cuidado, con apoyo del centro regulador. | N371: «La familia del paciente, que busca…» y «La autoridad de tránsito, que documenta…» asignan una gestión asistencial a personas o autoridades sin competencia para ello. | O371: Decreto 780 de 2016, (Decreto Único Reglamentario del Sector Salud); Resolución 3047 de 2008 | P371: SI | Q371: Media | R371: v2
A372: F0371 | B372: PS 2782 de 2026 - ESE 2 - HUHMP Neiva | C372: Referencia y contrarreferencia | D372: Técnico | E372: C124 | F372: Caso 124 | G372: A las 03:20 ingresa por urgencias un hombre politraumatizado en un accidente de tránsito. El vehículo no tenía póliza del seguro obligatorio vigente. El paciente requiere manejo en una institución de tercer nivel que el hospital no presta. El auxiliar de la oficina de referencia pregunta a quién debe dirigir la solicitud y quién asumirá el costo, porque el conductor asegura que la familia no tiene cómo pagar. | H372: Al no existir póliza vigente, la atención del accidentado se financia con cargo a: | I372: Los recursos previstos para eventos catastróficos y accidentes de tránsito que administra la ADRES | J372: El presupuesto de la institución que atiende, que luego lo incluye en su plan de saneamiento | K372: Los recursos propios de la entidad territorial donde ocurrió el accidente de tránsito e informar al médico tratante | L372: a | M372: Cuando no hay póliza, la atención de las víctimas de accidentes de tránsito se cubre con los recursos del mecanismo previsto para eventos catastróficos y accidentes de tránsito. | N372: «El presupuesto de la institución que…» traslada al prestador un costo con fuente definida y «Los recursos propios de la entidad…» invoca una fuente que no es la aplicable a este evento. | O372: Ley 100 de 1993, art. 167; Decreto 780 de 2016 | P372: SI | Q372: Media | R372: v2
A373: F0372 | B373: PS 2782 de 2026 - ESE 2 - HUHMP Neiva | C373: Referencia y contrarreferencia | D373: Técnico | E373: C124 | F373: Caso 124 | G373: A las 03:20 ingresa por urgencias un hombre politraumatizado en un accidente de tránsito. El vehículo no tenía póliza del seguro obligatorio vigente. El paciente requiere manejo en una institución de tercer nivel que el hospital no presta. El auxiliar de la oficina de referencia pregunta a quién debe dirigir la solicitud y quién asumirá el costo, porque el conductor asegura que la familia no tiene cómo pagar. | H373: Mientras se define el responsable del pago, la conducta correcta frente al paciente es: | I373: Solicitar a la familia un pagaré y suspender el traslado mientras lo firma | J373: Mantener la atención y continuar la gestión del traslado en condiciones seguras | K373: Aplazar el traslado y esperar que la aseguradora confirme la cobertura | L373: b | M373: La definición del pagador no puede afectar la continuidad de la atención ni la gestión del traslado. | N373: «Solicitar a la familia un pagaré…» y «Aplazar el traslado y esperar que…» condicionan una atención de urgencias a una garantía económica o a una confirmación administrativa. | O373: Ley 1751 de 2015, art. 14 | P373: SI | Q373: Media | R373: v2
... A918: F0917 | B918: PS 2782 de 2026 - ESE 2 - HUHMP Neiva | C918: Empleo publico y carrera administrativa | D918: Profesional | E918: C311 | F918: Capacitación, bienestar e incentivos | G918: El grupo de talento humano prepara los programas del año. Un profesional pregunta si un curso de posgrado puede pagarse con el plan de capacitación, si el día de la familia hace parte de bienestar y qué diferencia hay entre un estímulo y un incentivo. | H918: El reconocimiento al equipo de trabajo con mejor desempeño hace parte de | I918: El plan institucional de capacitación, que incluye la inducción y la reinducción del personal | J918: El plan de incentivos de la entidad | K918: El programa de bienestar social laboral | L918: b | M918: Los incentivos, pecuniarios y no pecuniarios, reconocen el desempeño de empleados y equipos. Ley 1567 de 1998, artículos 26 y 29. | N918: La capacitación desarrolla capacidades y el bienestar atiende calidad de vida: ninguno reconoce el desempeño. | O918: Ley 1567 de 1998, arts. 26 y 29 | P918: SI | Q918: Media | R918: v3

Sheet Comportamentales
A1: id | B1: competencia | C1: situacion | D1: a | E1: b | F1: c | G1: puntos_a | H1: puntos_b | I1: puntos_c | J1: activa | K1: tipo_v2 | L1: consigna | M1: invertida
A2: B0001 | B2: Orientación al usuario y al ciudadano | C2: Un usuario llega alterado porque le reprogramaron la cita por tercera vez. El agendamiento no depende de usted. | D2: Escucha, verifica en el sistema, explica la causa y gestiona con el área responsable una fecha concreta | E2: Le ofrece disculpas y le sugiere volver cuando haya menos gente | F2: Le explica que el trámite no depende de su área y le indica dónde reclamar | G2: 3 | H2: 1 | I2: 2 | J2: NO | L2: ¿Qué hace usted? | M2: NO
A3: B0002 | B3: Orientación al usuario y al ciudadano | C3: Una persona mayor no entiende el formato de consentimiento que debe firmar antes de un procedimiento. | D3: Pide al acompañante que firme para agilizar | E3: Le entrega el formato y le pide que lo lea con calma en la sala | F3: Explica en lenguaje sencillo, verifica que comprendió y solo entonces solicita la firma | G3: 1 | H3: 2 | I3: 3 | J3: NO | L3: ¿Qué hace usted? | M3: NO
A4: B0003 | B4: Orientación a resultados | C4: Un reporte obligatorio vence mañana y falta información de otra dependencia. | D4: Solicita por escrito lo que falta, informa el riesgo a su jefe y avanza con lo disponible | E4: Reporta datos estimados para cumplir el plazo | F4: Espera la información hasta el último momento y decide entonces | G4: 3 | H4: 1 | I4: 2 | J4: NO | L4: ¿Qué hace usted? | M4: NO
A5: B0004 | B5: Orientación a resultados | C5: Le asignan tres tareas urgentes el mismo día y no alcanza a hacerlas todas. | D5: Empieza por la más fácil para mostrar avance | E5: Prioriza según impacto y plazo, acuerda con su jefe el orden y comunica los tiempos | F5: Intenta las tres a la vez y entrega lo que alcance | G5: 2 | H5: 3 | I5: 1 | J5: NO | L5: ¿Qué hace usted? | M5: NO
A6: B0005 | B6: Transparencia | C6: Un proveedor con el que usted tramita un contrato le ofrece un obsequio de bajo valor. | D6: Lo rechaza verbalmente y no informa a nadie | E6: Lo acepta porque su valor es bajo y lo destina al fondo de empleados | F6: Rechaza el obsequio y deja constancia escrita del ofrecimiento ante su jefe inmediato | G6: 2 | H6: 1 | I6: 3 | J6: NO | L6: ¿Qué hace usted? | M6: NO
A7: B0006 | B7: Transparencia | C7: Un familiar suyo se presenta a un proceso contractual en el que usted participa. | D7: Continúa participando pero avisa verbalmente a un compañero | E7: Manifiesta el impedimento por escrito y se aparta del trámite | F7: Continúa porque confía en su imparcialidad | G7: 2 | H7: 3 | I7: 1 | J7: NO | L7: ¿Qué hace usted? | M7: NO
A8: B0007 | B8: Compromiso con la organización | C8: Detecta un error propio en un informe que ya llegó a la gerencia. | D8: Corrige el archivo compartido y espera a que alguien pregunte | E8: Guarda silencio porque el error es menor | F8: Informa de inmediato el error, remite la versión corregida y explica su impacto | G8: 2 | H8: 1 | I8: 3 | J8: NO | L8: ¿Qué hace usted? | M8: NO
A9: B0008 | B9: Compromiso con la organización | C9: Un compañero critica en público a la entidad frente a usuarios en la sala de espera. | D9: Cambia de tema y sigue con su trabajo | E9: Le propone en privado llevar el asunto a los canales internos y atiende a los usuarios | F9: Se suma a la crítica para no quedar mal con el compañero | G9: 2 | H9: 3 | I9: 1 | J9: NO | L9: ¿Qué hace usted? | M9: NO
A10: B0009 | B10: Trabajo en equipo | C10: Un compañero se retrasa por sobrecarga y la entrega del equipo está en riesgo. | D10: Propone al líder redistribuir tareas y apoya en lo que puede sin descuidar lo suyo | E10: Asume todo el trabajo del compañero sin informar a nadie | F10: Entrega su parte y deja constancia de que el retraso no es suyo | G10: 3 | H10: 1 | I10: 2 | J10: NO | L10: ¿Qué hace usted? | M10: NO
A11: B0010 | B11: Trabajo en equipo | C11: En una reunión, su propuesta es descartada por el grupo con argumentos técnicos. | D11: Acepta en silencio y se desentiende de la ejecución | E11: Insiste en su propuesta por fuera de la reunión | F11: Acoge la decisión, aporta a la alternativa elegida y deja registrada su observación | G11: 2 | H11: 1 | I11: 3 | J11: NO | L11: ¿Qué hace usted? | M11: NO
A12: B0011 | B12: Adaptación al cambio | C12: El hospital implementa un módulo nuevo del sistema de información y cambia su proceso. | D12: Participa en la capacitación, ajusta su proceso y reporta las dificultades que encuentra | E12: Mantiene el registro paralelo en papel para no cambiar | F12: Usa el módulo solo cuando es indispensable | G12: 3 | H12: 1 | I12: 2 | J12: NO | L12: ¿Qué hace usted? | M12: NO
A13: B0012 | B13: Adaptación al cambio | C13: Lo trasladan temporalmente a un servicio que no conoce. | D13: Manifiesta que no es su área y limita su aporte | E13: Espera a que el jefe del servicio le asigne tareas simples | F13: Solicita inducción, identifica los procedimientos críticos y pide retroalimentación | G13: 1 | H13: 2 | I13: 3 | J13: NO | L13: ¿Qué hace usted? | M13: NO
... A31: B0030 | B31: Gestión de procedimientos | C31: Un usuario le pide saltarse un paso del procedimiento por urgencia. | D31: Explica por qué existe el paso y busca la ruta prevista para casos urgentes | E31: Se lo salta por esta vez | F31: Le dice que no hay nada que hacer | G31: 3 | H31: 2 | I31: 1 | J31: NO | L31: ¿Qué hace usted? | M31: NO
A32: B0031 | B32: Orientación al usuario y al ciudadano | C32: Son las 11:40 y usted atiende el último turno antes del almuerzo. Llega una señora de otro municipio que viajó dos horas y trae la documentación incompleta: le falta un soporte que puede pedir por correo, pero tardaría dos días. Detrás hay cuatro personas esperando y su jefe insiste en cumplir el indicador de tiempo de atención. | D32: Le explica que sin el soporte no puede radicar y le entrega por escrito la lista de lo que debe traer | E32: Le recibe todo sin revisar para no demorar la fila y le dice que después la llaman si algo falta | F32: Recibe lo que trae, le indica con precisión cómo enviar el soporte faltante y le deja el trámite radicado | G32: 2 | H32: 1 | I32: 3 | J32: SI | K32: v2 | L32: ¿Qué hace usted? | M32: NO
A33: B0032 | B33: Orientación al usuario y al ciudadano | C33: Un usuario lleva veinte minutos discutiendo en voz alta porque su cita fue reprogramada. La programación no depende de usted y la sala está llena de gente esperando. Su compañera le sugiere que lo ignore hasta que se canse y el vigilante pregunta si lo retira del lugar. | D33: Escucha su reclamo en la ventanilla, le pide calma y le entrega el formato para presentar la queja formal | E33: Le explica que la programación no es su área y le indica en qué oficina puede reclamar por ese asunto | F33: Lo atiende en un espacio aparte, verifica su caso en el sistema y le da una respuesta con fecha concreta | G33: 2 | H33: 1 | I33: 3 | J33: SI | K33: v2 | L33: ¿Qué hace usted? | M33: NO
A34: B0033 | B34: Orientación a resultados | C34: El informe mensual vence mañana y falta un dato que depende de otra dependencia que no responde hace tres días. Su jefe está de comisión y no contesta. Entregar incompleto afecta el indicador del área; entregar tarde también, y ambos quedan registrados en el sistema de seguimiento. | D34: Reitera la solicitud por escrito, informa el riesgo al superior encargado y entrega con el dato pendiente identificado | E34: Entrega el informe con el dato en blanco y una nota que identifica cuál dependencia no lo remitió a tiempo | F34: Estima el dato con el promedio de los meses anteriores para poder entregar el informe completo a tiempo | G34: 3 | H34: 2 | I34: 1 | J34: SI | K34: v2 | L34: ¿Qué hace usted? | M34: NO
A35: B0034 | B35: Orientación a resultados | C35: Le asignan tres tareas para el mismo viernes: un reporte a un ente de control, una presentación para la junta directiva y la revisión de un procedimiento interno. Ninguna puede aplazarse sin costo, y su jefe le dice que las tres son prioritarias y que se organice como pueda. | D35: Trabaja en las tres de manera simultánea y entrega el viernes lo que haya logrado adelantar de cada una | E35: Empieza por la del ente de control, que tiene consecuencias legales, y avanza con las otras según alcance | F35: Estima el tiempo de cada una, propone al jefe un orden con fechas | G35: 1 | H35: 2 | I35: 3 | J35: SI | K35: v2 | L35: ¿Qué hace usted? | M35: NO
A36: B0035 | B36: Transparencia | C36: Un proveedor con el que usted tramita un contrato le envía por la fiesta de fin de año una canasta navideña a su casa, sin remitente visible. Usted la recibe sin saber de quién era y al día siguiente él se lo comenta entre risas en una llamada de trabajo. | D36: Conserva la canasta porque ya fue recibida y decide no volver a tratar temas personales con ese proveedor | E36: Devuelve la canasta al proveedor, le pide que no se repita y no informa el hecho dentro de la entidad | F36: Devuelve la canasta, deja constancia escrita del hecho ante su jefe y continúa el trámite con normalidad | G36: 1 | H36: 2 | I36: 3 | J36: SI | K36: v2 | L36: ¿Qué hace usted? | M36: NO
A37: B0036 | B37: Transparencia | C37: Su cuñado se presenta a una convocatoria de prestación de servicios en la que usted revisa las hojas de vida. Es el candidato con mejor perfil y la entidad necesita cubrir el cargo esta semana. Nadie en la oficina conoce el parentesco y su jefe le pide agilizar la evaluación. | D37: Declara el impedimento por escrito, se aparta de la evaluación y propone quién puede asumirla esta semana | E37: Le comenta el parentesco a su jefe de manera verbal y continúa la evaluación aplicando criterios objetivos | F37: Evalúa las hojas de vida y deja que sea el jefe quien tome la decisión final sobre la contratación | G37: 3 | H37: 2 | I37: 1 | J37: SI | K37: v2 | L37: ¿Qué hace usted? | M37: NO
A38: B0037 | B38: Compromiso con la organización | C38: Detecta que un informe suyo, ya enviado a la gerencia y citado en una reunión con el ente de control, tiene un error de cálculo que cambia una cifra en un ocho por ciento. Nadie lo ha notado. Corregirlo implica reconocer el error frente a quienes ya usaron el dato. | D38: Informa el error de inmediato, remite la versión corregida y precisa qué decisiones pudo haber afectado | E38: Deja el dato como está y ajusta los informes siguientes para que la serie quede consistente hacia adelante | F38: Corrige el archivo, lo reenvía con el asunto actualizado y espera a que alguien pregunte por la diferencia | G38: 3 | H38: 1 | I38: 2 | J38: SI | K38: v2 | L38: ¿Qué hace usted? | M38: NO
A39: B0038 | B39: Compromiso con la organización | C39: En una reunión con usuarios, un compañero critica en voz alta la gestión de la entidad y afirma que los procesos no sirven. Varios asistentes asienten. Usted comparte parte del diagnóstico, pero no la forma ni el lugar, y el compañero es más antiguo que usted en la institución. | D39: Guarda silencio en la reunión y después lleva el tema al comité interno donde corresponde tratarlo | E39: Reencauza la reunión hacia lo que sí puede resolverse y luego habla en privado con el compañero | F39: Aclara en el momento que esa es una opinión personal suya y continúa con el orden del día previsto | G39: 2 | H39: 3 | I39: 1 | J39: SI | K39: v2 | L39: ¿Qué hace usted? | M39: NO
A40: B0039 | B40: Trabajo en equipo | C40: Un compañero de su equipo está atrasado porque asumió el trabajo de otra persona que salió a incapacidad. La entrega conjunta es en dos días. Si usted lo apoya, descuida una tarea propia que también vence, y el líder del equipo aún no se ha enterado de la situación. | D40: Informa al líder el riesgo real, propone una redistribución con plazos y apoya en lo que pueda sostener | E40: Entrega su parte a tiempo y aclara por correo que el retraso del equipo no corresponde a su actividad | F40: Le ayuda con lo más urgente en horas adicionales y comenta la situación al líder cuando se entregue todo | G40: 3 | H40: 1 | I40: 2 | J40: SI | K40: v2 | L40: ¿Qué hace usted? | M40: NO
A41: B0040 | B41: Trabajo en equipo | C41: Otra área comete un error que afecta su proceso y usted debe rehacer el trabajo de dos días. El responsable es una persona con la que ya ha tenido roces. Su jefe le pregunta qué pasó delante de todo el equipo en la reunión de seguimiento semanal. | D41: Describe el hecho con datos, sin señalar personas, y propone un ajuste conjunto entre las dos áreas | E41: Explica que el error vino de la otra área y aclara que ya lo está corrigiendo por su cuenta | F41: Responde que hubo un inconveniente menor y habla luego del tema directamente con el responsable | G41: 3 | H41: 2 | I41: 1 | J41: SI | K41: v2 | L41: ¿Qué hace usted? | M41: NO
A42: B0041 | B42: Adaptación al cambio | C42: La entidad cambia el aplicativo con el que usted trabaja hace seis años. La nueva versión es más lenta en su tarea principal, aunque mejora el reporte global. Varios compañeros siguen usando el archivo antiguo en paralelo y el jefe no ha dicho nada al respecto. | D42: Adopta el aplicativo nuevo y resuelve como puede la demora, sin reportar la dificultad que encontró | E42: Mantiene el archivo antiguo para su tarea y usa el aplicativo solo cuando debe generar el reporte global | F42: Usa el aplicativo nuevo, documenta con datos dónde se pierde tiempo y lleva la observación al responsable | G42: 2 | H42: 1 | I42: 3 | J42: SI | K42: v2 | L42: ¿Qué hace usted? | M42: NO
A43: B0042 | B43: Adaptación al cambio | C43: Lo trasladan por tres meses a un servicio que no conoce, con procedimientos distintos y un equipo que ya tiene su ritmo. El jefe del servicio está ocupado y le dice que aprenda observando. La primera semana le asignan tareas para las que no tiene claridad. | D43: Observa una semana, toma notas y empieza a trabajar preguntando cuando encuentra algo que no comprende | E43: Solicita una inducción breve, identifica los procedimientos críticos y confirma cada duda antes de actuar | F43: Ejecuta las tareas asignadas replicando lo que ve hacer a los compañeros más antiguos del servicio | G43: 2 | H43: 3 | I43: 1 | J43: SI | K43: v2 | L43: ¿Qué hace usted? | M43: NO
... A169: B0168 | B169: Trabajo en equipo | C169: En la entrega del turno del puesto de control del aeropuerto, quien sale omite decir que un cargamento quedó pendiente de verificación. Usted lo descubre dos horas después revisando el registro. Es la tercera vez este mes que la entrega llega incompleta | D169: Registrar el hallazgo y comentarlo en la reunión mensual del grupo | E169: Hablar con esa persona y acordar una lista corta de puntos obligatorios | F169: Informar el hecho al coordinador para que él corrija al responsable | G169: 2 | H169: 3 | I169: 1 | J169: SI | K169: v3 | L169: ¿Cuál es la conducta más efectiva? | M169: NO

Sheet Resumen
A1: Solaris Merit Neiva - Resumen del banco
A3: Concurso | B3: PS 2782 de 2026 - ESE 2 - HUHMP Neiva
A4: Preguntas funcionales | B4: =COUNTA(Funcionales!A2:A2000) -> 917
A5: Casos funcionales | B5: =SUMPRODUCT((Funcionales!E2:E2000<>"")/COUNTIF(Funcionales!E2:E2000,Funcionales!E2:E2000&"")) -> 311
A6: Preguntas comportamentales | B6: =COUNTA(Comportamentales!A2:A500) -> 168
A7: Total preguntas | B7: =B4+B6 -> 1085
A9: Preguntas por eje
A10: Eje | B10: Preguntas | C10: Casos
A11: Sistema de salud y Ley 100 de 1993 | B11: =COUNTIF(Funcionales!$C$2:$C$2000,$A11) -> 67 | C11: =COUNTIF(Funcionales!$C$2:$C$2000,$A11)/3 -> 22.333333
A12: Ley 1751 de 2015 - derecho fundamental a la salud | B12: =COUNTIF(Funcionales!$C$2:$C$2000,$A12) -> 63 | C12: =COUNTIF(Funcionales!$C$2:$C$2000,$A12)/3 -> 21
A13: Habilitacion y calidad (Resolucion 3100 de 2019) | B13: =COUNTIF(Funcionales!$C$2:$C$2000,$A13) -> 60 | C13: =COUNTIF(Funcionales!$C$2:$C$2000,$A13)/3 -> 20
A14: Seguridad del paciente | B14: =COUNTIF(Funcionales!$C$2:$C$2000,$A14) -> 66 | C14: =COUNTIF(Funcionales!$C$2:$C$2000,$A14)/3 -> 22
A15: Historia clinica y proteccion de datos (Ley 1581 de 2012) | B15: =COUNTIF(Funcionales!$C$2:$C$2000,$A15) -> 63 | C15: =COUNTIF(Funcionales!$C$2:$C$2000,$A15)/3 -> 21
A16: Humanizacion y derechos del paciente | B16: =COUNTIF(Funcionales!$C$2:$C$2000,$A16) -> 54 | C16: =COUNTIF(Funcionales!$C$2:$C$2000,$A16)/3 -> 18
A17: Referencia y contrarreferencia | B17: =COUNTIF(Funcionales!$C$2:$C$2000,$A17) -> 51 | C17: =COUNTIF(Funcionales!$C$2:$C$2000,$A17)/3 -> 17
A18: Urgencias | B18: =COUNTIF(Funcionales!$C$2:$C$2000,$A18) -> 51 | C18: =COUNTIF(Funcionales!$C$2:$C$2000,$A18)/3 -> 17
A19: Gestion hospitalaria y organizacion de la E.S.E. | B19: =COUNTIF(Funcionales!$C$2:$C$2000,$A19) -> 87 | C19: =COUNTIF(Funcionales!$C$2:$C$2000,$A19)/3 -> 29
A20: Contratacion en la E.S.E. y transparencia | B20: =COUNTIF(Funcionales!$C$2:$C$2000,$A20) -> 54 | C20: =COUNTIF(Funcionales!$C$2:$C$2000,$A20)/3 -> 18
A21: Regimen disciplinario y CPACA | B21: =COUNTIF(Funcionales!$C$2:$C$2000,$A21) -> 103 | C21: =COUNTIF(Funcionales!$C$2:$C$2000,$A21)/3 -> 34.333333
A22: Precision juridica del verbo | B22: =COUNTIF(Funcionales!$C$2:$C$2000,$A22) -> 97 | C22: =COUNTIF(Funcionales!$C$2:$C$2000,$A22)/3 -> 32.333333
A23: TOTAL | B23: =SUM(B11:B22) -> 816 | C23: =SUM(C11:C22) -> 272

Sheet Instrucciones
A1: Solaris Merit Neiva - Banco de preguntas de práctica
A3: Concurso: Proceso de Selección No. 2782 de 2026 - Empresas Sociales del Estado 2
A4: Entidad: E.S.E. Hospital Universitario Hernando Moncaleano Perdomo (Neiva, Huila)
A5: Acuerdo de convocatoria: Acuerdo CNSC N° 36 del 9 de abril de 2026 - Anexo Técnico E.S.E. 2 Orden Territorial
A6: Niveles cubiertos: Profesional y Técnico
A8: AVISO IMPORTANTE
A9: Estas preguntas son de PRÁCTICA y fueron elaboradas a partir de la normativa pública citada en cada fila.
A10: NO son preguntas reales de una prueba de la CNSC: las pruebas tienen carácter reservado (Ley 909 de 2004, art. 31 num. 3).
A11: Este material no está afiliado, avalado ni patrocinado por la CNSC ni por la E.S.E. Hospital Universitario Hernando Moncaleano Perdomo.
A13: CÓMO EDITAR ESTE ARCHIVO
A14: 1. Hoja Funcionales: una fila por pregunta. Tres filas con el mismo caso_id comparten el mismo texto_caso (formato de caso con tres enunciados).
A15: 2. Columna respuesta: escriba únicamente a, b o c en minúscula.
... A49: 5. Si no se conoce el artículo con certeza, se deja la norma con su año y no se inventa el artículo.

Sheet Basicas
A1: id | B1: bloque | C1: componente | D1: dificultad | E1: caso | F1: estimulo | G1: enunciado | H1: a | I1: b | J1: c | K1: respuesta | L1: explicacion | M1: porque_no | N1: fuente | O1: activa | P1: ambito | Q1: en_banco_funcional
A2: CB001 | B2: Aptitudes | C2: Lectura crítica | D2: Alta | F2: La entidad publicó que el tiempo promedio de respuesta a las peticiones bajó de 12 a 8 días en el último semestre. El informe aclara que el promedio se calculó sobre las peticiones cerradas en el periodo y que 1.400 peticiones seguían abiertas al corte, algunas radicadas hace más de cuatro meses. | G2: El dato del promedio, tal como está calculado: | H2: Sobrestima la demora real, porque incluye peticiones de semestres anteriores | I2: Refleja la demora real, porque el promedio se calculó sobre casos cerrados | J2: Subestima la demora real, porque deja por fuera las peticiones aún abiertas | K2: c | L2: Al promediar solo lo cerrado, las peticiones más demoradas, que siguen abiertas, no entran en el cálculo y el promedio queda mejor de lo que es. | M2: Decir que refleja la realidad ignora las 1.400 abiertas; decir que la sobrestima invierte el sentido del sesgo. | O2: SI | P2: comun | Q2: no
A3: CB002 | B3: Aptitudes | C3: Lectura crítica | D3: Media | F3: La entidad publicó que el tiempo promedio de respuesta a las peticiones bajó de 12 a 8 días en el último semestre. El informe aclara que el promedio se calculó sobre las peticiones cerradas en el periodo y que 1.400 peticiones seguían abiertas al corte, algunas radicadas hace más de cuatro meses. | G3: Del texto se puede afirmar con certeza que: | H3: El promedio de días de las peticiones cerradas disminuyó frente al periodo anterior | I3: La entidad mejoró la atención al ciudadano durante el semestre analizado | J3: Las peticiones abiertas fueron radicadas todas hace más de cuatro meses | K3: a | L3: Lo único que el texto afirma es la caída del promedio de las cerradas; la mejora general y la antigüedad de todas las abiertas no se siguen de él. | M3: Afirmar la mejora general excede lo dicho, y el texto habla de algunas peticiones antiguas, no de todas. | O3: SI | P3: comun | Q3: no
A4: CB003 | B4: Aptitudes | C4: Lectura crítica | D4: Alta | F4: Un columnista sostiene que los concursos de méritos deberían eliminar la valoración de antecedentes, porque premia a quien tuvo dinero para estudiar posgrados. Reconoce que la experiencia también se valora, pero afirma que quien ya trabajó en el sector lleva ventaja. | G4: La estructura del argumento del columnista es: | H4: Una descripción del procedimiento de valoración que aplican los concursos de méritos | I4: Una comparación entre dos concursos que valoran de forma distinta los antecedentes | J4: Una propuesta apoyada en que el factor cuestionado favorece a quien ya tiene ventajas | K4: c | L4: El columnista propone eliminar un factor y lo sustenta en que ese factor reproduce ventajas previas. | M4: No hay descripción neutra del procedimiento ni comparación entre dos concursos: hay una tesis con su razón. | O4: SI | P4: comun | Q4: no
A5: CB004 | B5: Aptitudes | C5: Lectura crítica | D5: Media | F5: Un columnista sostiene que los concursos de méritos deberían eliminar la valoración de antecedentes, porque premia a quien tuvo dinero para estudiar posgrados. Reconoce que la experiencia también se valora, pero afirma que quien ya trabajó en el sector lleva ventaja. | G5: La concesión que hace el columnista consiste en: | H5: Admitir que la experiencia también se valora, aunque la considere otra fuente de ventaja | I5: Admitir que la valoración de antecedentes tiene un peso menor que las pruebas escritas | J5: Admitir que los posgrados mejoran el desempeño de quien ocupa el empleo público | K5: a | L5: Conceder es reconocer algo que juega en contra de la propia tesis: aquí reconoce que no solo se valoran posgrados. | M5: Ni el desempeño ni el peso porcentual aparecen en el texto: son añadidos del lector. | O5: SI | P5: comun | Q5: no
A6: CB005 | B6: Aptitudes | C6: Lectura crítica | D6: Basica | F6: Una circular interna dice: «Los servidores deberán responder las solicitudes dentro del término legal. Quien no pueda hacerlo informará al jefe inmediato antes del vencimiento, con la justificación correspondiente». | G6: Según la circular, informar al jefe procede cuando: | H6: La solicitud exige consultar a otra dependencia de la entidad | I6: Se prevé que no será posible responder dentro del término legal | J6: Ya venció el término legal y la solicitud sigue sin respuesta | K6: b | L6: La circular ata el aviso a la imposibilidad prevista y exige que ocurra antes del vencimiento. | M6: Avisar después del vencimiento contradice el texto, y consultar a otra área no es el supuesto que la circular regula. | O6: SI | P6: comun | Q6: no
A7: CB006 | B7: Aptitudes | C7: Lectura crítica | D7: Media | F7: Una circular interna dice: «Los servidores deberán responder las solicitudes dentro del término legal. Quien no pueda hacerlo informará al jefe inmediato antes del vencimiento, con la justificación correspondiente». | G7: La expresión «con la justificación correspondiente» significa que: | H7: El jefe inmediato debe autorizar por escrito la demora en la respuesta | I7: El aviso debe explicar por qué no se alcanza a responder en el término | J7: La demora queda excusada con el solo hecho de haber dado el aviso | K7: b | L7: La justificación califica al aviso: no basta con avisar, hay que decir la razón. | M7: La autorización del jefe y la excusa automática son efectos que el texto no establece. | O7: SI | P7: comun | Q7: no
A8: CB007 | B8: Aptitudes | C8: Lectura crítica | D8: Alta | F8: Dos informes analizan el mismo servicio. El primero concluye que la satisfacción subió porque el 78 % de los encuestados la calificó como buena. El segundo advierte que solo respondió el 9 % de los usuarios y que la encuesta se entregó al salir de consulta. | G8: La objeción del segundo informe apunta a: | H8: El porcentaje de satisfacción, que fue calculado con una fórmula equivocada | I8: La conclusión del primer informe, que contradice los datos que él mismo presenta | J8: La forma en que se recogieron los datos, que puede sesgar el resultado | K8: c | L8: El reparo es metodológico: pocos respondientes y un momento de aplicación que selecciona a cierto tipo de usuario. | M8: No se discute la aritmética del porcentaje ni se señala contradicción interna en el primer informe. | O8: SI | P8: comun | Q8: no
A9: CB008 | B9: Aptitudes | C9: Lectura crítica | D9: Media | F9: Dos informes analizan el mismo servicio. El primero concluye que la satisfacción subió porque el 78 % de los encuestados la calificó como buena. El segundo advierte que solo respondió el 9 % de los usuarios y que la encuesta se entregó al salir de consulta. | G9: Si ambos informes son correctos en sus datos, lo razonable es: | H9: Descartar la encuesta y repetirla con el mismo instrumento el semestre siguiente | I9: Concluir que la satisfacción real está cerca del 9 % de los usuarios del servicio | J9: Tomar el 78 % como el dato de quienes respondieron, no del conjunto de usuarios | K9: c | L9: El porcentaje describe a quienes contestaron; extenderlo al total exige suponer que los demás opinan igual. | M9: Descartar sin más pierde información, y confundir la tasa de respuesta con la satisfacción es un error de lectura. | O9: SI | P9: comun | Q9: no
A10: CB009 | B10: Aptitudes | C10: Razonamiento cuantitativo | D10: Basica | F10: Un área recibió 480 solicitudes en el trimestre y resolvió 372 dentro del término. | G10: El porcentaje de solicitudes resueltas a tiempo es: | H10: 72,5 % | I10: 82,5 % | J10: 77,5 % | K10: c | L10: 372 dividido entre 480 da 0,775, es decir 77,5 %. | M10: Los otros dos resultan de dividir mal o de restar el porcentaje de incumplidas al total de forma equivocada. | O10: SI | P10: comun | Q10: no
A11: CB010 | B11: Aptitudes | C11: Razonamiento cuantitativo | D11: Media | F11: Un área recibió 480 solicitudes en el trimestre y resolvió 372 dentro del término. | G11: Para llegar al 85 % de cumplimiento con las mismas 480 solicitudes, habría que resolver a tiempo: | H11: 36 solicitudes más de las que resolvió | I11: 30 solicitudes más de las que resolvió | J11: 42 solicitudes más de las que resolvió | K11: a | L11: El 85 % de 480 es 408; 408 menos 372 da 36 solicitudes adicionales. | M11: Las otras cifras salen de tomar el 85 % sobre las resueltas o de usar un total distinto al del trimestre. | O11: SI | P11: comun | Q11: no
A12: CB011 | B12: Aptitudes | C12: Razonamiento cuantitativo | D12: Media | F12: Un contrato de 90 millones se ejecutó así: 30 % en el primer trimestre, 45 % en el segundo y el resto en el tercero. | G12: El valor ejecutado en el tercer trimestre es: | H12: 25,0 millones | I12: 20,0 millones | J12: 22,5 millones | K12: c | L12: El resto es 100 % menos 75 %, o sea 25 %; el 25 % de 90 millones son 22,5 millones. | M12: Los otros valores salen de restar mal los porcentajes o de aplicar el 25 % a una base distinta. | O12: SI | P12: comun | Q12: no
A13: CB012 | B13: Aptitudes | C13: Razonamiento cuantitativo | D13: Alta | F13: Un contrato de 90 millones se ejecutó así: 30 % en el primer trimestre, 45 % en el segundo y el resto en el tercero. | G13: Si el contrato se adiciona en 20 % y el porcentaje ejecutado no cambia, el saldo por ejecutar al cierre del segundo trimestre es: | H13: 22,5 millones | I13: 31,5 millones | J13: 27,0 millones | K13: c | L13: El valor adicionado es 108 millones; el 25 % pendiente de 108 son 27 millones. | M13: Un resultado mantiene el saldo sin adicionar y el otro aplica el 20 % al saldo en vez de al contrato. | O13: SI | P13: comun | Q13: no
... A115: CB114 | B115: Aptitudes | C115: Ofimática y gestión documental | D115: Basica | F115: Guarda un archivo de trabajo en el escritorio del computador. | G115: El riesgo principal de esa práctica es: | H115: Que el archivo abra más lento al iniciar sesión | I115: Que el archivo ocupe espacio en el disco duro | J115: Que el archivo no quede respaldado ni visible | K115: c | L115: Lo grave es que si el equipo falla o alguien más lo necesita, el archivo no está disponible. | M115: El espacio y la velocidad son molestias, no la pérdida de la información. | O115: SI | P115: comun | Q115: no
